pystomp/StompClient.py
pystomp/__init__.py
pystomp-0.0.1.dist-info/METADATA
pystomp-0.0.1.dist-info/WHEEL
pystomp-0.0.1.dist-info/top_level.txt
pystomp-0.0.1.dist-info/RECORD
